pydator/__init__.py
pydator/base_rule.py
pydator/exceptions.py
pydator/validator.py
pydator/rules/__init__.py
pydator/rules/boolean.py
pydator/rules/contains.py
pydator/rules/date.py
pydator/rules/email.py
pydator/rules/float_rule.py
pydator/rules/in_rule.py
pydator/rules/integer.py
pydator/rules/max.py
pydator/rules/mime.py
pydator/rules/min.py
pydator/rules/number.py
pydator/rules/regex.py
pydator/rules/required_rule.py
pydator/rules/string_rule.py
pydator/rules/url.py
pydator-1.2.1.dist-info/licenses/LICENSE
pydator-1.2.1.dist-info/METADATA
pydator-1.2.1.dist-info/WHEEL
pydator-1.2.1.dist-info/top_level.txt
pydator-1.2.1.dist-info/RECORD
