Metadata-Version: 2.4
Name: pydator
Version: 1.2.1
Summary: A simple and hands-on validation library for Python.
Author-email: Seam Uddin <seamuddin.me@gmail.com>
License-Expression: MIT
Project-URL: Homepage, https://github.com/seamuddin/pydator
Project-URL: Repository, https://github.com/seamuddin/pydator
Project-URL: BugTracker, https://github.com/seamuddin/pydator/issues
Project-URL: Documentation, https://github.com/seamuddin/pydator#readme
Classifier: Development Status :: 4 - Beta
Classifier: Intended Audience :: Developers
Classifier: Programming Language :: Python :: 3
Classifier: Programming Language :: Python :: 3.6
Classifier: Programming Language :: Python :: 3.7
Classifier: Programming Language :: Python :: 3.8
Classifier: Programming Language :: Python :: 3.9
Classifier: Programming Language :: Python :: 3.10
Classifier: Programming Language :: Python :: 3.11
Classifier: Programming Language :: Python :: 3.12
Classifier: Topic :: Software Development :: Libraries
Classifier: Topic :: Utilities
Requires-Python: >=3.6
License-File: LICENSE
Dynamic: license-file
